noisereduce/__init__.py
noisereduce/generate_noise.py
noisereduce/noisereduce.py
noisereduce/plotting.py
noisereduce/utils.py
noisereduce/spectralgate/__init__.py
noisereduce/spectralgate/base.py
noisereduce/spectralgate/nonstationary.py
noisereduce/spectralgate/stationary.py
noisereduce/spectralgate/streamed_torch_gate.py
noisereduce/spectralgate/utils.py
noisereduce/torchgate/__init__.py
noisereduce/torchgate/torchgate.py
noisereduce/torchgate/utils.py
noisereduce-3.0.3.dist-info/LICENSE
noisereduce-3.0.3.dist-info/METADATA
noisereduce-3.0.3.dist-info/WHEEL
noisereduce-3.0.3.dist-info/top_level.txt
noisereduce-3.0.3.dist-info/RECORD
