Metadata-Version: 2.1
Name: noisereduce
Version: 3.0.3
Summary: Noise reduction using Spectral Gating in Python
Home-page: https://github.com/timsainb/noisereduce
Author: Tim Sainburg
License: MIT
Classifier: Programming Language :: Python :: 3
Classifier: License :: OSI Approved :: BSD License
Classifier: Operating System :: OS Independent
Classifier: Intended Audience :: Science/Research
Classifier: Topic :: Education
Classifier: Topic :: Scientific/Engineering
License-File: LICENSE
Requires-Dist: scipy
Requires-Dist: matplotlib
Requires-Dist: numpy
Requires-Dist: tqdm
Requires-Dist: joblib
Provides-Extra: pytorch
Requires-Dist: torch>=1.9.0; extra == "pytorch"
